lawyer/__init__.py
lawyer/__init__.pyi
lawyer/exceptions.py
lawyer/exceptions.pyi
lawyer/parsers.py
lawyer/parsers.pyi
lawyer-2.5.0.dist-info/licenses/LICENSE
lawyer-2.5.0.dist-info/METADATA
lawyer-2.5.0.dist-info/WHEEL
lawyer-2.5.0.dist-info/top_level.txt
lawyer-2.5.0.dist-info/RECORD
