Metadata-Version: 2.4
Name: lawyer
Version: 2.5.0
Summary: A redefined argument parser designed for ease of use.
Author-email: Soumyo Deep Gupta <deep@d33p0st.in>
Maintainer-email: Soumyo Deep Gupta <deep@d33p0st.in>
License-Expression: MIT
Classifier: Development Status :: 4 - Beta
Classifier: Operating System :: OS Independent
Requires-Python: >=3.11
License-File: LICENSE
Requires-Dist: colorama
Dynamic: license-file
